divelogpy/__init__.py
divelogpy/air_integration.py
divelogpy/cli.py
divelogpy/client.py
divelogpy/decoders.py
divelogpy/examples/__init__.py
divelogpy/models.py
divelogpy/plotting.py
divelogpy/pnf_constants.py
divelogpy/pnf_decoder.py
divelogpy/sensor_checks.py
divelogpy/sensor_report.py
divelogpy/timeseries.py
divelogpy/utils.py
divelogpy-0.1.7.dist-info/METADATA
divelogpy-0.1.7.dist-info/WHEEL
divelogpy-0.1.7.dist-info/entry_points.txt
divelogpy-0.1.7.dist-info/RECORD
