Metadata-Version: 2.3
Name: divelogpy
Version: 0.1.7
Summary: Dive log analysis workspace
Requires-Python: >=3.11,<4.0
Classifier: Programming Language :: Python :: 3
Classifier: Programming Language :: Python :: 3.11
Classifier: Programming Language :: Python :: 3.12
Classifier: Programming Language :: Python :: 3.13
Requires-Dist: kaleido (==0.2.1)
Requires-Dist: matplotlib (>=3.9,<4.0)
Requires-Dist: notebook (>=7.2,<8.0)
Requires-Dist: pandas (>=2.2,<3.0)
Requires-Dist: plotly (>=6.3.0,<7.0.0)
Requires-Dist: python-dotenv (>=1.0,<2.0)
Requires-Dist: scikit-learn (>=1.7.2,<2.0.0)
Requires-Dist: scipy (>=1.16.2,<2.0.0)
Requires-Dist: statsmodels (>=0.14.5,<0.15.0)
